amieci/VERSION
amieci/__init__.py
amieci/api.py
amieci/exceptions.py
amieci/highlevel.py
amieci/sse.py
amieci-0.0.8.dist-info/METADATA
amieci-0.0.8.dist-info/WHEEL
amieci-0.0.8.dist-info/top_level.txt
amieci-0.0.8.dist-info/zip-safe
amieci-0.0.8.dist-info/RECORD
