Metadata-Version: 2.1
Name: amieci
Version: 0.0.8
Summary: The python API for amie
Home-page: https://www.amie.ai
Author: johannes beil
Author-email: jb@amie.dk
License: private
Platform: UNKNOWN
Classifier: Programming Language :: Python :: 3
Classifier: License :: Other/Proprietary License
Classifier: Operating System :: OS Independent
Classifier: Development Status :: 2 - Pre-Alpha
Requires-Dist: requests
Requires-Dist: pandas
